pytoulbar2-0.0.0.5.dist-info/RECORD
pytoulbar2-0.0.0.5.dist-info/WHEEL
pytoulbar2-0.0.0.5.dist-info/top_level.txt
pytoulbar2-0.0.0.5.dist-info/METADATA
pytoulbar2-0.0.0.5.dist-info/licenses/LICENSE
pytoulbar2/__init__.py
pytoulbar2/pytoulbar2.py
pytoulbar2/pytb2.cpython-312-darwin.so
pytoulbar2/.dylibs/libboost_iostreams.dylib
pytoulbar2/.dylibs/libicudata.77.1.dylib
pytoulbar2/.dylibs/libboost_graph.dylib
pytoulbar2/.dylibs/libicuuc.77.1.dylib
pytoulbar2/.dylibs/libboost_random.dylib
pytoulbar2/.dylibs/libboost_regex.dylib
pytoulbar2/.dylibs/libboost_serialization.dylib
pytoulbar2/.dylibs/liblzma.5.dylib
pytoulbar2/.dylibs/libgmp.10.dylib
pytoulbar2/.dylibs/libicui18n.77.1.dylib
pytoulbar2/.dylibs/libzstd.1.5.7.dylib
