Metadata-Version: 2.1
Name: pytoulbar2
Version: 0.0.0.5
Summary: ToulBar2 Python package
Home-page: http://miat.inrae.fr/toulbar2
Author: ToulBar2 team
Author-email: thomas.schiex@inrae.fr
License: MIT
Keywords: optimization graphical-model
Classifier: License :: OSI Approved :: MIT License
Classifier: Topic :: Scientific/Engineering :: Artificial Intelligence
Classifier: Topic :: Scientific/Engineering :: Mathematics
Classifier: Programming Language :: C++
Classifier: Programming Language :: Python :: 3
Classifier: Intended Audience :: Science/Research
License-File: LICENSE
